{
  "release": {
    "channel": "stable"
  },
  "sharedFolders": [
    {
      "path": "/",
      "guid": "e514e3e5-a847-4acb-9d30-d9cd7ef18348",
      "relay": "530e0c13-00da-42d1-938c-60485fb3e347",
      "sync": {
        "images": true,
        "audio": true,
        "videos": true,
        "pdfs": true,
        "otherTypes": false
      }
    }
  ],
  "endpoints": {},
  "enableDocumentStatus": false,
  "enableNewLinkFormat": false,
  "enableDeltaLogging": false,
  "enableDocumentHistory": false,
  "enableEditorTweens": false,
  "enableNetworkLogging": false,
  "enableCanvasSync": false,
  "enableVerifyUploads": false,
  "enableAutomaticDiffResolution": true,
  "enableDiscordLogin": false,
  "enableSelfManageHosts": true,
  "enableToasts": true,
  "enablePresenceAvatars": true,
  "enableLiveEmbeds": true,
  "enablePreviewViewHooks": true,
  "enableMetadataViewHooks": true,
  "enableKanbanView": true,
  "debugging": false,
  "login": {
    "provider": "github"
  },
  "enableSyncMenu": true,
  "enableAttachmentSync": true,
  "enableDocumentServer": true,
  "enableMicrosoftLogin": true,
  "enableGitHubLogin": true,
  "enableOIDCLogin": true
}